nz_seqtech/__init__.py
nz_seqtech/classical_ml_models.py
nz_seqtech/classical_operations.py
nz_seqtech/quantum_dna_encoding.py
nz_seqtech/quantum_ml_models.py
nz_seqtech-0.2.13.dist-info/LICENSE
nz_seqtech-0.2.13.dist-info/METADATA
nz_seqtech-0.2.13.dist-info/WHEEL
nz_seqtech-0.2.13.dist-info/top_level.txt
nz_seqtech-0.2.13.dist-info/RECORD
