Metadata-Version: 2.1
Name: nz_seqtech
Version: 0.2.13
Summary: A library for DNA sequence encoding in quantum machine learning
Home-page: https://nz-seqtech.com/
Author: Nouhaila Innan
Author-email: nouhailainnan@gmail.com
License: Apache
Project-URL: Documentation, https://nz-seqtech.readthedocs.io/
License-File: LICENSE
Requires-Dist: wheel
Requires-Dist: numpy >=1.20.0
Requires-Dist: pandas >=1.2.0
Requires-Dist: scikit-learn >=0.24.0
Requires-Dist: qiskit ==0.43.1
Requires-Dist: matplotlib >=3.3.4
Requires-Dist: qiskit-algorithms
Requires-Dist: qiskit-machine-learning ==0.6.1
Requires-Dist: qiskit-aer ==0.12.0
Requires-Dist: qiskit-ibmq-provider ==0.20.2
Requires-Dist: pylatexenc
